{
  "name": "Marie George",
  "age": 23,
  "address": {
    "street": "Jevova Pass",
    "city": "Kevoaf",
    "state": "WY",
    "zip": "47607"
  },
  "contact": {
    "phone": "(519) 544-1178",
    "servicePhone": "800528822"
  },
  "birthday": "1998-09-23T13:06:57.076Z",
  "ip": "201.136.245.100",
  "foo": "bar",
  "profile": {
    "about": "Fekata bos da fab puujwu omemte redorazit canad ew lubkofe tew zog wuopeofo cat azoiftav cej. Urehuep ojiga jidavu zo uwimatav uh kom sar pecdubow ciwev arumubi muzahgu zirrata ku iwogusise. Gusemajun badbu wiket horer utied deg mo hieme cef dipo vovneup uz. Ofud gedulam gila ot wawunji colinpes dow lecjov uweun jisnojowu rocobo ruwog kuvzag. Poruk hu sif suipeka hetnodi cat wankoz apdurup fot deiriam ki cudafo tepmir unlot kaw id afe. Mohvo ev bozjaubo jolek jafepi noiwtip cet ama cijizaw eb tu gupuhket idnadci lisug leravnev duubmuc.",
    "bio": "Aprukwo jijen wahcur sof odo leta avluvsev fivowim rufnegu loazi le belirfup riwhe ap ahce. Idhif fe ap tuwcig oce abearofak pa ridgi peuv ago heltito tuni ciok holawzol la ojavhiz le mincit. Za nu haluwa ovu le um mifata wirege fumral gan pirbe omabse hajwerib vu durzufpa pepozluz. Ceb vofe neljeh budaob fa waur lo kena vufuunu fos pel jilap nulal mih so. Kezvi urudusat pan wolsof voglitven tasogwel vimabva ufbov bow ob ci siajo zih."
  },
  "apiKey": "e188cf8ad3c92262a7b7721e9efe444dcfe70b08db19dd7712c1d18cde3f6aa6",
  "currency": {
    "code": "MWK",
    "name": "Malawi Kwacha"
  }
}