{
  "name": "Garrett Holmes",
  "age": 47,
  "address": {
    "street": "Utizuh Glen",
    "city": "Tavijiw",
    "state": "IA",
    "zip": "23962"
  },
  "contact": {
    "phone": "(653) 471-9214",
    "servicePhone": "800821516"
  },
  "birthday": "1990-06-10T07:20:45.689Z",
  "ip": "238.27.19.207",
  "foo": "bar",
  "profile": {
    "about": "Epedahlud nijwanuz pigonora wap jaoggul pozib mawik somtojes tuv ogesuwov ko uc. Ejoiguve luurivej hofuraf lajwu cakfad vocero olhe fojpip vavecjut bilovloj hoc niosone opaati. Zagsicles ujafi hidacdo fe lo kisbud ora pipcoaki zevanot bec eviepje noniho tehez zuggo be. Duhicnu colenog uvaeme se le esu carotiri eha ovhetza ijivef si datki wuklo.",
    "bio": "Ud wuvi utifub diur dikahitob kukunik lod to vosekfab gateop buzig koru pehaf cefuji juza oduka. De un dusajo wim vewo haw zone nekrel sogtoc romu hu ju bo wef zuhfi gozilode or hu. Aseos hadmejwow rekoluvo nupgowlip no pohelo inki kusmol aresiuti ta ekezul ufazu mab egojaj den. Taukifaj nakihob joggowsij wiwra to befed guz hilulu zo ajis dubiwit mukubkiv dumupip ucirehbin iteojeisi. Obji uf nofopdo ta tezena diwhin beb fad ezogehpe fup fifodjap po juggahli de eduka vo icopaivi. Zizcawere jutugbog av uma gok loeze dadjusik resmozga popeg nefeno cojhe so liwonpi ofa no lebwo suleffam gizeh. Gelzu nunada fofu zomomuw pekopvur fupopoj jabo kepti hanaf fuvmo tec wehut zo ojdumola fi."
  },
  "apiKey": "f927046fa1b583e0967a5a6fc24ea8dcfde5aaeb055603f24dc54e30eebde401",
  "currency": {
    "code": "JMD",
    "name": "Jamaica Dollar"
  }
}