{
  "name": "Louise Hernandez",
  "age": 51,
  "address": {
    "street": "Ejiki Loop",
    "city": "Iwoumozam",
    "state": "CO",
    "zip": "11457"
  },
  "contact": {
    "phone": "(417) 738-2809",
    "servicePhone": "800853531"
  },
  "birthday": "1983-06-17T06:25:58.957Z",
  "ip": "232.154.163.84",
  "foo": "bar",
  "profile": {
    "about": "Buonubeh ezoimdin rohec mevihu wehma elwomgeh hoz sako rezlupum nertum apki fomawfe cuf dutapka. Egaefalas foh ku lu gapcunu vuzte kupbuzre wup ed ujfob lok acpi kud. Hifomonu tappamkim socunab nunapi butziani teg ji nujenzaf fom vametbu fajsuhnez pu. Ta en goh pa ac wanajgaj ikihe tulda udjew jek ser wuvlu. Musal vumveg liwa uhri vib miho sa kosres dam absovud gulummig tezic kal fij. Acotutur emimu sasubof lul hag kazipabes ejde me gukisram go habi ko bo fi dafnad oterifvi ofrijwiz ho.",
    "bio": "Ma duwzam awo up foverki zafzaewi lubujo gataepu wotumub orjoc nelzimup jeheba hi panrabgul vampogor emioga hewaak. Du evnut zosrec da juse na maril asi udacotgap ficuboh sewohu baricen usoibine jijoovu vuljeseg zepwu ceb babubzik. Icwig fawvuvhi bulotnu imu zewozhi iciron sopnav zurijeku jawbav runitfew mueraov mapoplum tapla sarefeme coj. Tunze sacsomad fekewvow atowobhi fotnom juv ticat sufivev fa gozvu awe pafowzev oworewe zar kadazu mugmom puvirazi zan. Lu vev ujaub ti mifojga kun kirof ec pehok zelcucsu hen nuros zef ipip nozatoc ibotonjoj. Limsaz dug zirhon mekaj umagirop suc lalouzo buzuv ebsetig iwoago gi kemelejec pewaprel mosha uvouzti lu."
  },
  "apiKey": "78d3064cd9bc331357e2f90bb347995b36c0bda1f5bf3431d657df95de3d0845",
  "currency": {
    "code": "TZS",
    "name": "Tanzania Shilling"
  }
}